mkmqr/__init__.py
mkmqr/__main__.py
mkmqr/__version.py
mkmqr/util.py
mkmqr/binary/__init__.py
mkmqr/binary/array.py
mkmqr/binary/matrix.py
mkmqr/error_correction/__init__.py
mkmqr/error_correction/polynomial_ring.py
mkmqr/error_correction/reed_solomon_code.py
mkmqr/error_correction/residue_field.py
mkmqr/factory/__init__.py
mkmqr/factory/segment.py
mkmqr/factory/symbol.py
mkmqr/matrix/__init__.py
mkmqr/matrix/matrix_codeword.py
mkmqr/matrix/matrix_format_information.py
mkmqr/matrix/matrix_function_pattern.py
mkmqr/matrix/matrix_mask.py
mkmqr/model/__init__.py
mkmqr/model/error.py
mkmqr/model/error_correction_level.py
mkmqr/model/mask.py
mkmqr/model/mode.py
mkmqr/model/values.py
mkmqr/model/version.py
mkmqr/optimization/__init__.py
mkmqr/optimization/adapter.py
mkmqr/optimization/text_model.py
mkmqr/optimization/util.py
mkmqr/optimization/algorithm/__init__.py
mkmqr/optimization/algorithm/opt_brute_force.py
mkmqr/optimization/algorithm/opt_hill_climbing.py
mkmqr-0.6.2.dist-info/LICENSE
mkmqr-0.6.2.dist-info/METADATA
mkmqr-0.6.2.dist-info/WHEEL
mkmqr-0.6.2.dist-info/entry_points.txt
mkmqr-0.6.2.dist-info/top_level.txt
mkmqr-0.6.2.dist-info/RECORD
