Metadata-Version: 2.1
Name: mkmqr
Version: 0.6.2
Summary: This is a package to make micro QR codes.
Author: Toshiki Kamiya
Author-email: tkamiya22@gmail.com
License: MIT License
Project-URL: Source Code, https://github.com/tkamiya22/mkmqr
Project-URL: Bug Tracker, https://github.com/tkamiya22/mkmqr/issues
Classifier: Programming Language :: Python :: 3
Classifier: Programming Language :: Python :: 3.8
License-File: LICENSE
Requires-Dist: numpy (>=1.20.0)
Requires-Dist: Pillow (>=9.1.0)
